opfer/artifacts.py
opfer/attributes.py
opfer/blob.py
opfer/core.py
opfer/errors.py
opfer/inspect.py
opfer/logging.py
opfer/provider.py
opfer/retry.py
opfer/tracing.py
opfer/types.py
opfer/workflow.py
opfer/extensions/google_genai.py
opfer/extensions/opentelemetry.py
opfer-0.1.0.dist-info/METADATA
opfer-0.1.0.dist-info/WHEEL
opfer-0.1.0.dist-info/licenses/LICENSE
opfer-0.1.0.dist-info/RECORD
