Metadata-Version: 2.4
Name: opfer
Version: 0.1.0
License-File: LICENSE
Requires-Python: >=3.13
Requires-Dist: pillow>=12.0.0
Requires-Dist: pydantic>=2.12.5
Provides-Extra: google-genai
Requires-Dist: google-genai>=1.53.0; extra == 'google-genai'
Provides-Extra: opentelemetry
Requires-Dist: opentelemetry-api>=1.39.1; extra == 'opentelemetry'
Requires-Dist: opentelemetry-exporter-otlp-proto-grpc>=1.39.1; extra == 'opentelemetry'
Requires-Dist: opentelemetry-sdk>=1.39.1; extra == 'opentelemetry'
